cvpack/__init__.py
cvpack/_version.py
cvpack/angle.py
cvpack/atomic_function.py
cvpack/attraction_strength.py
cvpack/base_custom_function.py
cvpack/base_path_cv.py
cvpack/base_radius_of_gyration.py
cvpack/base_rmsd.py
cvpack/base_rmsd_content.py
cvpack/centroid_function.py
cvpack/collective_variable.py
cvpack/composite_rmsd.py
cvpack/distance.py
cvpack/helix_angle_content.py
cvpack/helix_hbond_content.py
cvpack/helix_rmsd_content.py
cvpack/helix_torsion_content.py
cvpack/meta_collective_variable.py
cvpack/number_of_contacts.py
cvpack/openmm_force_wrapper.py
cvpack/path_in_cv_space.py
cvpack/path_in_rmsd_space.py
cvpack/py.typed
cvpack/radius_of_gyration.py
cvpack/radius_of_gyration_sq.py
cvpack/residue_coordination.py
cvpack/rmsd.py
cvpack/sheet_rmsd_content.py
cvpack/shortest_distance.py
cvpack/torsion.py
cvpack/torsion_similarity.py
cvpack/utils.py
cvpack/data/ideal_alpha_helix.csv
cvpack/data/ideal_antiparallel_beta_sheet.csv
cvpack/data/ideal_parallel_beta_sheet.csv
cvpack/path/__init__.py
cvpack/path/path.py
cvpack/reporting/__init__.py
cvpack/reporting/custom_writer.py
cvpack/reporting/cv_writer.py
cvpack/reporting/meta_cv_writer.py
cvpack/reporting/state_data_reporter.py
cvpack/serialization/__init__.py
cvpack/serialization/serialization.py
cvpack/tests/__init__.py
cvpack/tests/test_cvpack.py
cvpack/units/__init__.py
cvpack/units/units.py
cvpack-0.12.2.dist-info/LICENSE
cvpack-0.12.2.dist-info/METADATA
cvpack-0.12.2.dist-info/WHEEL
cvpack-0.12.2.dist-info/top_level.txt
cvpack-0.12.2.dist-info/RECORD
