Metadata-Version: 2.1
Name: cvpack
Version: 0.12.2
Summary: Useful Collective Variables for OpenMM
Author-email: Charlles Abreu <craabreu@gmail.com>
License: MIT
Project-URL: Source, https://github.com/RedesignScience/cvpack/
Project-URL: Documentation, https://redesignscience.github.io/cvpack/latest
Classifier: License :: OSI Approved :: MIT License
Classifier: Programming Language :: Python :: 3
Requires-Python: >=3.8
License-File: LICENSE
Requires-Dist: numpy
Requires-Dist: openmm
Requires-Dist: pyyaml
Provides-Extra: test
Requires-Dist: pytest >=6.1.2 ; extra == 'test'
Requires-Dist: pytest-runner ; extra == 'test'
